dixa/__init__.py
dixa/base_client.py
dixa/dixa_client.py
dixa/errors.py
dixa/models.py
dixa/utils.py
dixa-0.1.0.dist-info/METADATA
dixa-0.1.0.dist-info/WHEEL
dixa-0.1.0.dist-info/top_level.txt
dixa-0.1.0.dist-info/RECORD
