Metadata-Version: 2.1
Name: dixa
Version: 0.1.0
Summary: Dixa Developer Kit for Python
Home-page: https://github.com/humanforest/dixa-python
Author: José Duarte
Author-email: jose.duarte@humanforest.co.uk
License: UNKNOWN
Keywords: dixa
Platform: UNKNOWN
Classifier: Development Status :: 4 - Beta
Classifier: Intended Audience :: Developers
Classifier: Natural Language :: English
Classifier: Programming Language :: Python :: 3
Classifier: Programming Language :: Python :: 3.6
Classifier: Programming Language :: Python :: 3.7
Classifier: Programming Language :: Python :: 3.8
Classifier: Programming Language :: Python :: 3.9
Classifier: Programming Language :: Python :: 3.10
Requires-Python: >=3.6
Requires-Dist: pydantic
Requires-Dist: pandas
Requires-Dist: requests
Requires-Dist: phonenumbers
Requires-Dist: pydantic[email]
